{
  "version": "7",
  "dialect": "postgresql",
  "entries": [
    {
      "idx": 0,
      "version": "7",
      "when": 1778144906891,
      "tag": "0000_woozy_black_knight",
      "breakpoints": true
    },
    {
      "idx": 1,
      "version": "7",
      "when": 1778412362008,
      "tag": "0001_fantastic_jane_foster",
      "breakpoints": true
    },
    {
      "idx": 2,
      "version": "7",
      "when": 1778645986706,
      "tag": "0002_wakeful_nehzno",
      "breakpoints": true
    },
    {
      "idx": 3,
      "version": "7",
      "when": 1778824027816,
      "tag": "0003_ancient_vision",
      "breakpoints": true
    }
  ]
}